metis_fn/__init__.py
metis_fn/chronos.py
metis_fn/cond.py
metis_fn/error.py
metis_fn/fn.py
metis_fn/monad.py
metis_fn/record.py
metis_fn/singleton.py
metis_fn-0.1.1.dist-info/METADATA
metis_fn-0.1.1.dist-info/WHEEL
metis_fn-0.1.1.dist-info/RECORD
