Metadata-Version: 2.1
Name: metis-fn
Version: 0.1.1
Summary: 
Author: Col Perks
Author-email: wild.fauve@gmail.com
Requires-Python: >=3.11,<4.0
Classifier: Programming Language :: Python :: 3
Classifier: Programming Language :: Python :: 3.11
Classifier: Programming Language :: Python :: 3.12
Requires-Dist: isoduration (>=20.11.0,<21.0.0)
Requires-Dist: pendulum (>=3.0.0,<4.0.0)
Requires-Dist: pymonad (>=2.4.0,<3.0.0)
